gooddata_flight_server/__init__.py
gooddata_flight_server/_version.py
gooddata_flight_server/cli.py
gooddata_flight_server/exceptions.py
gooddata_flight_server/metrics.py
gooddata_flight_server/py.typed
gooddata_flight_server/config/__init__.py
gooddata_flight_server/config/config.py
gooddata_flight_server/errors/__init__.py
gooddata_flight_server/errors/error_code.py
gooddata_flight_server/errors/error_info.py
gooddata_flight_server/health/__init__.py
gooddata_flight_server/health/health_check_http_server.py
gooddata_flight_server/health/server_health_monitor.py
gooddata_flight_server/server/__init__.py
gooddata_flight_server/server/base.py
gooddata_flight_server/server/default.logging.ini
gooddata_flight_server/server/server_base.py
gooddata_flight_server/server/server_main.py
gooddata_flight_server/server/auth/__init__.py
gooddata_flight_server/server/auth/auth_middleware.py
gooddata_flight_server/server/auth/token_verifier.py
gooddata_flight_server/server/auth/token_verifier_factory.py
gooddata_flight_server/server/auth/token_verifier_impl.py
gooddata_flight_server/server/flight_rpc/__init__.py
gooddata_flight_server/server/flight_rpc/flight_middleware.py
gooddata_flight_server/server/flight_rpc/flight_server.py
gooddata_flight_server/server/flight_rpc/flight_service.py
gooddata_flight_server/server/flight_rpc/server_methods.py
gooddata_flight_server/tasks/__init__.py
gooddata_flight_server/tasks/base.py
gooddata_flight_server/tasks/metrics.py
gooddata_flight_server/tasks/task.py
gooddata_flight_server/tasks/task_error.py
gooddata_flight_server/tasks/task_executor.py
gooddata_flight_server/tasks/task_result.py
gooddata_flight_server/tasks/temporal_container.py
gooddata_flight_server/tasks/thread_task_executor.py
gooddata_flight_server/utils/__init__.py
gooddata_flight_server/utils/libc_utils.py
gooddata_flight_server/utils/logging.py
gooddata_flight_server/utils/methods_discovery.py
gooddata_flight_server/utils/otel_tracing.py
gooddata_flight_server-1.58.0.dist-info/METADATA
gooddata_flight_server-1.58.0.dist-info/WHEEL
gooddata_flight_server-1.58.0.dist-info/entry_points.txt
gooddata_flight_server-1.58.0.dist-info/licenses/LICENSE.txt
gooddata_flight_server-1.58.0.dist-info/RECORD
