Metadata-Version: 2.4
Name: gooddata-flight-server
Version: 1.58.0
Summary: Flight RPC server to host custom functions
Project-URL: Documentation, https://gooddata-flight-server.readthedocs.io/en/v1.58.0
Project-URL: Source, https://github.com/gooddata/gooddata-python-sdk
Author-email: GoodData <support@gooddata.com>
License-Expression: MIT
License-File: LICENSE.txt
Keywords: analytics,business,cloud,custom functions,flight,flight rpc,gooddata,headless,headless-bi,intelligence,layer,metrics,native,rpc,semantic,sql
Classifier: Development Status :: 4 - Beta
Classifier: Environment :: Console
Classifier: Programming Language :: Python :: 3.10
Classifier: Programming Language :: Python :: 3.11
Classifier: Programming Language :: Python :: 3.12
Classifier: Programming Language :: Python :: 3.13
Classifier: Programming Language :: Python :: 3.14
Classifier: Topic :: Database
Classifier: Topic :: Scientific/Engineering
Classifier: Topic :: Software Development
Classifier: Typing :: Typed
Requires-Python: >=3.10
Requires-Dist: dynaconf<4.0.0,>=3.1.11
Requires-Dist: opentelemetry-api<=2.0.0,>=1.24.0
Requires-Dist: opentelemetry-sdk<=2.0.0,>=1.24.0
Requires-Dist: orjson<4.0.0,>=3.8.5
Requires-Dist: prometheus-client~=0.20.0
Requires-Dist: pyarrow>=16.1.0
Requires-Dist: readerwriterlock~=1.0.9
Requires-Dist: structlog<25.0.0,>=24.0.0
